{
    "title": "Deposition of Dr. Jessica C. Hawkins",
    "content": "IN THE CIRCUIT COURT OF COOK COUNTY, ILLINOIS\n\nPlaintiffs: Susan J. Harris, et al.\nDefendants: Leonard P. Franklin, et al.\nCASE NUMBER: CAB08-13579\n\nCOPY DATE: March 15, 2023\n\n## DEPOSITION\nPursuant to notice, the following videotaped deposition of DR. JESSICA C. HAWKINS was taken before me, Samuel T. Rhodes, Notary Public, in and for the State of Illinois, at 221 Lexington Avenue, Suite 400, Chicago, Illinois 60601, commencing at 10:13 a.m., when present on behalf of the respective parties:\n\n### APPEARANCES\n- DAVID R. HUNTER, ESQUIRE (Plaintiffs)\n- SARAH T. WILLIAMS, ESQUIRE & MARCUS A. REID, ESQUIRE (Defendant - United Auto Insurance Company)\n- ALSO PRESENT: Mark Stevens, Video Operator\n\n### INDEX\n#### WITNESS\n- DR. JESSICA C. HAWKINS\n  - Voir Dire Examination by Mr. Reid: Page 5\n  - Direct Examination by Mr. Reid: Page 11\n  - Cross Examination by Mr. Hunter: Page 25\n  - Redirect Examination by Mr. Reid: Page 55\n\n### EXHIBITS\n- No. 1: Curriculum Vitae - Page 4\n- No. 2: Treatment Records - Page 8\n- No. 3: Correspondence Log - Page 29 (Retained by Counsel)\n\nEXAMINATION OF DR. JESSICA C. HAWKINS\nDr. Jessica C. Hawkins was called as a witness by counsel for the Defendant, United Auto Insurance Company, and after having been duly sworn by the Notary Reporter, was examined and testified as follows:\n\n### CERTIFICATION\nI, Samuel T. Rhodes, Notary Public in and for the State of Illinois, hereby certify that the witness personally appeared before me and was duly sworn, and that the foregoing transcript is a full, true, and accurate record of the evidence given by the witness.\n\n### March 15, 2023\nSamuel T. Rhodes, Notary Public\nState of Illinois",
    "extension": "txt",
    "fileSize": 22560,
    "labels": ["Deposition"],
    "source": "Circuit Court of Cook County, Illinois",
    "meta": "{\"case_number\": \"CAB08-13579\", \"court\": \"Circuit Court of Cook County, Illinois\", \"witness\": \"Dr. Jessica C. Hawkins\", \"notary_public\": \"Samuel T. Rhodes\", \"deposition_date\": \"March 15, 2023\"}",
    "metadata": "Deposition transcript for court proceedings.",
    "summary": "**Case Summary:**\n\n- **Case Number:** CAB08-13579\n- **Court:** Circuit Court of Cook County, Illinois\n- **Parties:**\n  - **Plaintiffs:** Susan J. Harris, et al.\n  - **Defendants:** Leonard P. Franklin, et al.\n- **Deposition Details:**\n  - **Witness:** Dr. Jessica C. Hawkins\n  - **Date:** March 15, 2023\n  - **Location:** 221 Lexington Avenue, Suite 400, Chicago, Illinois 60601\n- **Representation:**\n  - **Plaintiffs:** David R. Hunter, Esquire (Hunter & Fuller, LLP)\n  - **Defendant (United Auto Insurance Company):** Sarah T. Williams, Esquire, and Marcus A. Reid, Esquire (Law Offices of Keaton, Reed & Associates)\n- **Examination:**\n  - **Voir Dire Examination:** Conducted by Mr. Reid (Page 5)\n  - **Direct Examination:** Conducted by Mr. Reid (Page 11)\n  - **Cross Examination:** Conducted by Mr. Hunter (Page 25)\n  - **Redirect Examination:** Conducted by Mr. Reid (Page 55)\n- **Exhibits:**\n  - **No. 1:** Curriculum Vitae (Page 4)\n  - **No. 2:** Treatment Records (Page 8)\n  - **No. 3:** Correspondence Log (Page 29, retained by counsel)"
  }
  