{
    "title": "Deposition of Dr. Emily V. Hartford",
    "content": "IN THE SUPERIOR COURT FOR CLARK COUNTY, NEVADA\n\nPlaintiffs: John A. Maxwell and Jane E. Maxwell\nDefendant: Harrison Automotive, LLC\nCASE NUMBER: CR29-05874\n\nCOPY DATE: September 15, 2023\n\n## DEPOSITION\nPursuant to notice, the following videotaped deposition of DR. EMILY V. HARTFORD was taken before me, Susan T. Clarke, Notary Public, in and for the State of Nevada, at 221 Sunrise Valley Road, Suite 320, Henderson, Nevada 89014, commencing at 10:00 a.m., when present on behalf of the respective parties:\n\n### APPEARANCES\n- DAVID K. RYAN, ESQUIRE (Plaintiffs)\n- MONICA L. TRAN, ESQUIRE (Defendant - Harrison Automotive, LLC)\n- ALSO PRESENT: Alex Rivera, Video Operator\n\n### INDEX\n#### WITNESS\n- DR. EMILY V. HARTFORD\n  - Voir Dire Examination by Ms. Tran: Page 5\n  - Direct Examination by Ms. Tran: Page 10\n  - Cross Examination by Mr. Ryan: Page 22\n  - Redirect Examination by Ms. Tran: Page 40\n\n### EXHIBITS\n- No. 1: Curriculum Vitae - Page 3\n- No. 2: Police Reports - Page 8\n- No. 3: Repair Invoices - Page 25 (Retained by Counsel)\n\nEXAMINATION OF DR. EMILY V. HARTFORD\nDr. Emily V. Hartford was called as a witness by counsel for the Defendant, Harrison Automotive, LLC, and after having been duly sworn by the Notary Reporter, was examined and testified as follows:\n\n### CERTIFICATION\nI hereby certify that I, Susan T. Clarke, am a Notary Public in and for the State of Nevada, and that the foregoing is a true and accurate transcription of the deposition of Dr. Emily V. Hartford, taken at the above-stated time and place.\n\nSusan T. Clarke, Notary Public\nMy Commission Expires: March 30, 2025\n\nEND OF TRANSCRIPT",
    "extension": "txt",
    "fileSize": 19800,
    "labels": ["Deposition"],
    "source": "Superior Court for Clark County, Nevada",
    "meta": "{\"case_number\": \"CR29-05874\", \"court\": \"Superior Court for Clark County, Nevada\", \"witness\": \"Dr. Emily V. Hartford\", \"notary_public\": \"Susan T. Clarke\", \"deposition_date\": \"September 15, 2023\"}",
    "metadata": "Deposition transcript for court proceedings.",
    "summary": "**Case Summary:**\n\n- **Case Number:** CR29-05874\n- **Court:** Superior Court for Clark County, Nevada\n- **Parties:**\n  - **Plaintiffs:** John A. Maxwell and Jane E. Maxwell\n  - **Defendant:** Harrison Automotive, LLC\n- **Deposition Details:**\n  - **Witness:** Dr. Emily V. Hartford\n  - **Date:** September 15, 2023\n  - **Location:** 221 Sunrise Valley Road, Suite 320, Henderson, Nevada 89014\n- **Attorneys:**\n  - **Plaintiffs:** David K. Ryan, Esquire (Ryan & Hart Associates)\n  - **Defendant:** Monica L. Tran, Esquire (Law Office of Douglas R. Shaw)\n- **Examination:**\n  - **Voir Dire Examination:** Conducted by Ms. Tran (Page 5)\n  - **Direct Examination:** Conducted by Ms. Tran (Page 10)\n  - **Cross Examination:** Conducted by Mr. Ryan (Page 22)\n  - **Redirect Examination:** Conducted by Ms. Tran (Page 40)\n- **Exhibits:**\n  - **No. 1:** Curriculum Vitae (Page 3)\n  - **No. 2:** Police Reports (Page 8)\n  - **No. 3:** Repair Invoices (Page 25, retained by counsel)"
  }
  