{
    "title": "Deposition of Dr. Martha L. Ingram",
    "content": "IN THE CIRCUIT COURT FOR FAIRFAX COUNTY, VIRGINIA\n\nPlaintiffs: Maria Lopez, et al.\nDefendants: Nathan B. Caldwell, et al.\nCASE NUMBER: CL23-09567\n\nCOPY DATE: March 12, 2023\n\n## DEPOSITION\nPursuant to notice, the following videotaped deposition of MARTHA L. INGRAM, PH.D. was taken before me, Samuel T. Andrews, Notary Public, in and for the State of Virginia, at 9801 Braddock Road, Suite 400, Fairfax, Virginia 22032, commencing at 10:02 a.m., when present on behalf of the respective parties:\n\n### APPEARANCES\n- JAMES R. SANDERS, ESQUIRE (Plaintiffs)\n- ELLEN C. MARTIN, ESQUIRE & THOMAS E. FIELDS, ESQUIRE (Defendant - Nathan B. Caldwell)\n- ALSO PRESENT: Michael Tan, Video Operator\n\n### INDEX\n#### WITNESS\n- MARTHA L. INGRAM, PH.D.\n  - Voir Dire Examination by Ms. Martin: Page 5\n  - Direct Examination by Ms. Martin: Page 8\n  - Cross Examination by Mr. Sanders: Page 20\n  - Redirect Examination by Ms. Martin: Page 50\n\n### EXHIBITS\n- No. 1: Curriculum Vitae - Page 4\n- No. 2: Financial Records - Page 6\n- No. 3: Correspondence - Page 35 (Retained by Counsel)\n\nEXAMINATION OF MARTHA L. INGRAM, PH.D.\nMartha L. Ingram, Ph.D., was called as a witness by counsel for the Defendant, Nathan B. Caldwell, and after having been duly sworn by the Notary Reporter, was examined and testified as follows:\n\n### CERTIFICATE OF COURT REPORTER\nI, Samuel T. Andrews, Notary Public in and for the Commonwealth of Virginia, do hereby certify that the witness, Dr. Martha L. Ingram, was duly sworn by me and that the foregoing deposition is a true and accurate record of the testimony given by the witness.\n\nGiven under my hand this 12th day of March, 2023.\nSamuel T. Andrews, Notary Public\nMy commission expires: August 14, 2025",
    "extension": "txt",
    "fileSize": 21000,
    "labels": ["Deposition"],
    "source": "Circuit Court for Fairfax County, Virginia",
    "meta": "{\"case_number\": \"CL23-09567\", \"court\": \"Circuit Court for Fairfax County, Virginia\", \"witness\": \"Dr. Martha L. Ingram\", \"notary_public\": \"Samuel T. Andrews\", \"deposition_date\": \"March 12, 2023\"}",
    "metadata": "Deposition transcript for court proceedings.",
    "summary": "**Case Summary:**\n\n- **Case Number:** CL23-09567\n- **Court:** Circuit Court for Fairfax County, Virginia\n- **Parties:**\n  - **Plaintiffs:** Maria Lopez, et al.\n  - **Defendants:** Nathan B. Caldwell, et al.\n- **Deposition Details:**\n  - **Date:** March 12, 2023\n  - **Location:** 9801 Braddock Road, Suite 400, Fairfax, Virginia 22032\n  - **Witness:** Martha L. Ingram, Ph.D.\n  - **Notary Public:** Samuel T. Andrews\n- **Examination:**\n  - **Voir Dire Examination:** Conducted by Ellen C. Martin, Esquire (Page 5)\n  - **Direct Examination:** Conducted by Ellen C. Martin, Esquire (Page 8)\n  - **Cross Examination:** Conducted by James R. Sanders, Esquire (Page 20)\n  - **Redirect Examination:** Conducted by Ellen C. Martin, Esquire (Page 50)\n- **Exhibits:**\n  - **No. 1:** Curriculum Vitae (Page 4)\n  - **No. 2:** Financial Records (Page 6)\n  - **No. 3:** Correspondence (Page 35, retained by counsel)"
  }
  